{
  "title": "TOEIC | Vocab - 5 Ä‘á»™ng tá»« thÆ°á»ng gáº·p Part 5 (BÃ i 1) | accomplish, achieve, acknowledge",
  "description": "ğŸ“š BÃ i 1: 5 Äá»™ng tá»« thÆ°á»ng gáº·p trong TOEIC Part 5\n\nTrong video nÃ y báº¡n sáº½ há»c:\nâœ… accomplish /É™ËˆkÉ‘ËmplÉªÊƒ/ - hoÃ n thÃ nh\nâœ… achieve /É™ËˆtÊƒiËv/ - Ä‘áº¡t Ä‘Æ°á»£c\nâœ… acknowledge /É™kËˆnÉ‘ËlÉªdÊ’/ - cÃ´ng nháº­n\nâœ… acquire /É™ËˆkwaÉªÉ™r/ - thu Ä‘Æ°á»£c\nâœ… adapt /É™ËˆdÃ¦pt/ - thÃ­ch nghi\n\nğŸ¯ Ná»™i dung:\n0:00 Giá»›i thiá»‡u\n0:15 Tá»« 1: Accomplish\n0:37 Tá»« 2: Achieve\n0:59 Tá»« 3: Acknowledge\n1:20 Tá»« 4: Acquire\n1:40 Tá»« 5: Adapt\n2:04 Quiz kiá»ƒm tra\n2:51 TÃ³m táº¯t\n\nğŸ“Œ Collocations quan trá»ng:\nâ€¢ accomplish a goal / accomplish a task\nâ€¢ achieve success / achieve results\nâ€¢ acknowledge receipt\nâ€¢ acquire skills / acquire knowledge\nâ€¢ adapt to changes\n\nğŸ‘‰ BÃ i tiáº¿p theo: adequate, adhere, adjacent, adjust, administer\n\nğŸ”” ÄÄƒng kÃ½ kÃªnh Ä‘á»ƒ há»c TOEIC má»—i ngÃ y!\n\n#TOEIC #TOEICVocabulary #Há»cTiáº¿ngAnh #Part5 #Tá»«Vá»±ngTOEIC",
  "tags": [
    "TOEIC",
    "TOEIC vocabulary",
    "tá»« vá»±ng TOEIC",
    "há»c TOEIC",
    "TOEIC Part 5",
    "accomplish",
    "achieve",
    "acknowledge",
    "acquire",
    "adapt",
    "luyá»‡n thi TOEIC",
    "tiáº¿ng Anh giao tiáº¿p",
    "English vocabulary",
    "TOEIC 2025"
  ],
  "category": "Education",
  "language": "vi",
  "playlist": "TOEIC Vocabulary Series",
  "chapters": [
    {"time": "0:00", "title": "Giá»›i thiá»‡u"},
    {"time": "0:15", "title": "Tá»« 1: Accomplish"},
    {"time": "0:37", "title": "Tá»« 2: Achieve"},
    {"time": "0:59", "title": "Tá»« 3: Acknowledge"},
    {"time": "1:20", "title": "Tá»« 4: Acquire"},
    {"time": "1:40", "title": "Tá»« 5: Adapt"},
    {"time": "2:04", "title": "Quiz kiá»ƒm tra"},
    {"time": "2:51", "title": "TÃ³m táº¯t"}
  ],
  "words": [
    {
      "word": "accomplish",
      "ipa": "/É™ËˆkÉ‘ËmplÉªÊƒ/",
      "meaning": "hoÃ n thÃ nh, Ä‘áº¡t Ä‘Æ°á»£c",
      "collocations": ["accomplish a goal", "accomplish a task"]
    },
    {
      "word": "achieve",
      "ipa": "/É™ËˆtÊƒiËv/",
      "meaning": "Ä‘áº¡t Ä‘Æ°á»£c, giÃ nh Ä‘Æ°á»£c",
      "collocations": ["achieve success", "achieve results"]
    },
    {
      "word": "acknowledge",
      "ipa": "/É™kËˆnÉ‘ËlÉªdÊ’/",
      "meaning": "thá»«a nháº­n, cÃ´ng nháº­n",
      "collocations": ["acknowledge receipt"]
    },
    {
      "word": "acquire",
      "ipa": "/É™ËˆkwaÉªÉ™r/",
      "meaning": "cÃ³ Ä‘Æ°á»£c, thu Ä‘Æ°á»£c, mua láº¡i",
      "collocations": ["acquire skills", "acquire knowledge", "acquire a company"]
    },
    {
      "word": "adapt",
      "ipa": "/É™ËˆdÃ¦pt/",
      "meaning": "thÃ­ch nghi, Ä‘iá»u chá»‰nh",
      "collocations": ["adapt to changes", "adapt to new environment"]
    }
  ],
  "next_lesson": {
    "number": 2,
    "words": ["adequate", "adhere", "adjacent", "adjust", "administer"]
  }
}
